{"airports":{"3X6uHPIP6EitENnOPEEK":{"date":{"_seconds":1698054927,"_nanoseconds":77000000},"airportName":"Chhatrapati Shivaji Maharaj International Airport","airportLng":"72.8628087","country":"India","enable":true,"cityLocation":"Mumbai","state":"Maharashtra","id":"3X6uHPIP6EitENnOPEEK","airportLat":"19.0902179"},"9VVGLTbz9mhw2kzUC2Xn":{"date":{"_seconds":1698179745,"_nanoseconds":220000000},"country":"Algeria","airportName":"gfgfgffgfgfgfg","airportLng":"3.3018971","enable":true,"cityLocation":"Rouïba","id":"9VVGLTbz9mhw2kzUC2Xn","state":"Wilaya d'Alger","airportLat":"36.7087796"},"Ay2B3xAjJQKhG1fJtEaK":{"date":{"_seconds":1697635233,"_nanoseconds":237000000},"airportName":"Sardar Vallabhbhai Patel International Airport","country":"India","airportLng":"72.626571","cityLocation":"Ahmedabad","id":"Ay2B3xAjJQKhG1fJtEaK","state":"Gujarat","airportLat":"23.0734262","enable":true},"GLBsBroeilhGSFOKa7mb":{"date":{"_seconds":1697635198,"_nanoseconds":980000000},"airportName":"Rajkot International Airport","airportLng":"71.0329185","country":"India","cityLocation":"Hirasar","id":"GLBsBroeilhGSFOKa7mb","state":"Gujarat","airportLat":"22.3799807","enable":true},"Jv12PpdTYXGlCJKeSuR5":{"date":{"_seconds":1697717070,"_nanoseconds":232000000},"airportName":"Surat","airportLng":"72.83106070000001","country":"India","cityLocation":"Surat","state":"Gujarat","id":"Jv12PpdTYXGlCJKeSuR5","airportLat":"21.1702401","enable":true},"R2IUxkYpLVfM7PaavjU5":{"date":{"_seconds":1698234604,"_nanoseconds":439000000},"country":"India","airportName":"Air Force Station Bhuj","airportLng":"69.6781069","enable":true,"cityLocation":"Bhuj","id":"R2IUxkYpLVfM7PaavjU5","state":"Gujarat","airportLat":"23.2774959"},"cK93Qp3exR14yAwfDvzB":{"date":{"_seconds":1697833264,"_nanoseconds":232000000},"airportName":"Kuala Lumpur International Airport","country":"Malaysia","airportLng":"101.7043235","cityLocation":"Sepang","id":"cK93Qp3exR14yAwfDvzB","state":"Selangor","airportLat":"2.7542289","enable":true},"cfzffkTLIxJRLnf5KS6D":{"date":{"_seconds":1698290075,"_nanoseconds":989000000},"country":"Canadá","airportName":"Tututu Space","airportLng":"-73.5802507","enable":true,"cityLocation":"Montreal","id":"cfzffkTLIxJRLnf5KS6D","state":"Quebec","airportLat":"45.4931795"},"lkQF38xh57Z2iMt0MGJo":{"date":{"_seconds":1698055082,"_nanoseconds":759000000},"airportName":"Mumbai Airport T2 International","country":"India","airportLng":"72.8744502","enable":true,"cityLocation":"Mumbai","id":"lkQF38xh57Z2iMt0MGJo","state":"Maharashtra","airportLat":"19.1010177"},"ovRn2BqTdd0DXhRbrJcs":{"date":{"_seconds":1698216733,"_nanoseconds":255000000},"country":"India","airportName":"Bhuj Airport","airportLng":"69.66394799999999","enable":true,"cityLocation":"Bhuj","id":"ovRn2BqTdd0DXhRbrJcs","state":"Gujarat","airportLat":"23.2755333"},"pnVmkUkIMCoVL90MW7J3":{"date":{"_seconds":1698234378,"_nanoseconds":44000000},"country":"India","airportName":"Kukma Main Bajar Road","airportLng":"69.77776109999999","enable":true,"cityLocation":"Kukma","id":"pnVmkUkIMCoVL90MW7J3","state":"Gujarat","airportLat":"23.21751"}}}